sitter/__init__.py
sitter/setting.py
sitter/sitter.py
sitter/util.py
sitter/utils.py
sitter-0.1.3.dist-info/LICENSE
sitter-0.1.3.dist-info/METADATA
sitter-0.1.3.dist-info/WHEEL
sitter-0.1.3.dist-info/entry_points.txt
sitter-0.1.3.dist-info/top_level.txt
sitter-0.1.3.dist-info/RECORD
