Metadata-Version: 2.1
Name: sitter
Version: 0.1.3
Author: St·Kali
Author-email: clarkmonkey@163.com
License: MIT
License-File: LICENSE
Requires-Dist: cache3
